{
  "rules": {
    ".read": false,
    ".write": false,

    "ft_planning_v1":              { ".read": "auth != null && auth.token.role != 'bakker'", ".write": "auth != null && auth.token.role != 'bakker'" },
    "ft_planning_outlook_archief": { ".read": "auth != null && auth.token.role != 'bakker'", ".write": "auth != null && auth.token.role != 'bakker'" },

    "ft_planning_backup": {
      ".read": "auth != null && auth.token.role != 'bakker'",
      "$ts": {
        ".write": "auth != null && auth.token.role != 'bakker' && (!data.exists() || !newData.exists())"
      }
    },

    "ft_ops_v1":          { ".read": "auth != null && auth.token.role != 'bakker'", ".write": "auth != null && auth.token.role != 'bakker'" },
    "ft_ops_v2": {
      ".read":  "auth != null",
      ".write": "auth != null && auth.token.role != 'bakker'",
      "$id": {
        ".write": "auth != null && (auth.token.role != 'bakker' || newData.exists())"
      }
    },
    "ft_priority_v1":          { ".read": "auth != null && auth.token.role != 'bakker'", ".write": "auth != null && auth.token.role != 'bakker'" },
    "ft_laadlijst_v1":         { ".read": "auth != null && auth.token.role != 'bakker'", ".write": "auth != null && auth.token.role != 'bakker'" },
    "ft_laadlijsten_v1":       { ".read": "auth != null && auth.token.role != 'bakker'", ".write": "auth != null && auth.token.role != 'bakker'" },
    "ft_horeca_laadlijst_v1":  { ".read": "auth != null && auth.token.role != 'bakker'", ".write": "auth != null && auth.token.role != 'bakker'" },
    "ft_eindstock_v1":         { ".read": "auth != null && auth.token.role != 'bakker'", ".write": "auth != null && auth.token.role != 'bakker'" },
    "ft_fiches_v1":            { ".read": "auth != null && auth.token.role != 'bakker'", ".write": "auth != null && auth.token.role != 'bakker'" },
    "ft_notities_v1": {
      ".read":  "auth != null",
      ".write": "auth != null && auth.token.role != 'bakker'",
      "$id": {
        ".write": "auth != null && (auth.token.role != 'bakker' || newData.exists())"
      }
    },
    "ft_qrcodes_meta_v1": {
      ".read":  "auth != null",
      ".write": "auth != null && auth.token.role != 'bakker'"
    },
    "ft_qrcodes_v1": {
      ".read":  "auth != null",
      ".write": "auth != null && auth.token.role != 'bakker'"
    },
    "ft_stroomaanvraag_v1":   { ".read": "auth != null && auth.token.role != 'bakker'", ".write": "auth != null && auth.token.role != 'bakker'" },
    "ft_bestellingen_v1":     { ".read": "auth != null && auth.token.role != 'bakker'", ".write": "auth != null && auth.token.role != 'bakker'" },
    "ft_bestel_catalogus_v1": { ".read": "auth != null && auth.token.role != 'bakker'", ".write": "auth != null && auth.token.role != 'bakker'" },
    "ft_archief_v1":          { ".read": "auth != null && auth.token.role != 'bakker'", ".write": "auth != null && auth.token.role != 'bakker'" },
    "ft_trucks_v1":           { ".read": "auth != null && auth.token.role != 'bakker'", ".write": "auth != null && auth.token.role != 'bakker'" },
    "ft_poets_history":       { ".read": "auth != null && auth.token.role != 'bakker'", ".write": "auth != null && auth.token.role != 'bakker'" },
    "foldtable_requests":     { ".read": "auth != null && auth.token.role != 'bakker'", ".write": "auth != null && auth.token.role != 'bakker'" },
    "ocb_keuringen": {
      ".read":  "auth != null",
      ".write": "auth != null && auth.token.role != 'bakker'"
    },
    "vet_tonnen":             { ".read": "auth != null && auth.token.role != 'bakker'", ".write": "auth != null && auth.token.role != 'bakker'" },

    "_userActivity": {
      ".read": "auth != null && auth.token.role == 'admin'",
      "$uid": {
        ".write": "auth != null && auth.uid == $uid && !auth.token.firebase.sign_in_provider.matches(/^anonymous$/i)",
        ".read":  "auth != null && (auth.uid == $uid || auth.token.role == 'admin')",
        "lastSeen":       { ".validate": "newData.isNumber()" },
        "lastLogin":      { ".validate": "newData.isNumber()" },
        "lastLogout":     { ".validate": "newData.isNumber()" },
        "loginCount":     { ".validate": "newData.isNumber()" },
        "email":          { ".validate": "newData.isString() && newData.val().length < 200" },
        "displayName":    { ".validate": "newData.isString() && newData.val().length < 200" },
        "provider":       { ".validate": "newData.isString() && newData.val().length < 40" },
        "userAgent":      { ".validate": "newData.isString() && newData.val().length < 400" },
        "loginHistory": {
          "$ts": {
            ".validate": "newData.hasChildren()",
            "type":      { ".validate": "newData.isString() && newData.val().length < 20" },
            "provider":  { ".validate": "newData.isString() && newData.val().length < 40" },
            "userAgent": { ".validate": "newData.isString() && newData.val().length < 400" },
            "$other":    { ".validate": false }
          }
        },
        "$other": { ".validate": false }
      }
    }
  }
}
